data4llm/Data4LLM.py
data4llm/__init__.py
data4llm-0.4.1.dist-info/LICENSE.txt
data4llm-0.4.1.dist-info/METADATA
data4llm-0.4.1.dist-info/WHEEL
data4llm-0.4.1.dist-info/top_level.txt
data4llm-0.4.1.dist-info/RECORD
