Metadata-Version: 2.1
Name: data4llm
Version: 0.4.1
Summary: Add apply_multi and other bugs fix
Home-page: https://github.com/SWEENEYHE/Data4LLM
Author: SweeneyHe
Author-email: sweeneyandhe@gmail.com
Classifier: Programming Language :: Python :: 3
Classifier: License :: OSI Approved :: MIT License
Classifier: Operating System :: OS Independent
Requires-Python: >=3.8
License-File: LICENSE.txt
